MANIFEST.in
README.rst
setup.cfg
setup.py
version.py
src/cgcloud/__init__.py
src/cgcloud/spark/__init__.py
src/cgcloud/spark/spark_box.py
src/cgcloud/spark/spark_cluster.py
src/cgcloud/spark/test/__init__.py
src/cgcloud/spark/test/conftest.py
src/cgcloud/spark/test/test_spark.py
src/cgcloud_spark.egg-info/PKG-INFO
src/cgcloud_spark.egg-info/SOURCES.txt
src/cgcloud_spark.egg-info/dependency_links.txt
src/cgcloud_spark.egg-info/namespace_packages.txt
src/cgcloud_spark.egg-info/requires.txt
src/cgcloud_spark.egg-info/top_level.txt