Metadata-Version: 1.0
Name: cgcloud-spark
Version: 1.5.6
Summary: Setup and manage a Apache Spark cluster in EC2
Home-page: https://github.com/BD2KGenomics/cgcloud
Author: Hannes Schmidt
Author-email: hannes@ucsc.edu
License: UNKNOWN
Platform: UNKNOWN
